README.txt
setup.py
pyumpf.egg-info/PKG-INFO
pyumpf.egg-info/SOURCES.txt
pyumpf.egg-info/dependency_links.txt
pyumpf.egg-info/top_level.txt
umpf/__init__.py
umpf/umpf.py