Metadata-Version: 1.0
Name: pyumpf
Version: 0.1.1
Summary: Python Unified Multiprocessing Parallel Functions
Home-page: https://github.com/afaulconbridge/pyumpf
Author: Adam Faulconbridge
Author-email: afaulconbridge@googlemail.com
License: UNKNOWN
Platform: UNKNOWN
Classifier: Development Status :: 3 - Alpha
Classifier: Intended Audience :: Developers
Classifier: License :: OSI Approved :: BSD License
Classifier: Natural Language :: English
Classifier: Operating System :: OS Independent
Classifier: Programming Language :: Python
Classifier: Programming Language :: Python :: 2.6
Classifier: Programming Language :: Python :: 2.7
Classifier: Topic :: Software Development :: Libraries :: Python Modules
